MasterLattice/JSON2YAML.py
MasterLattice/__init__.py
MasterLattice/_version.py
MasterLattice/Data_Files/DCP_200um_G1200um.csv
MasterLattice/Data_Files/DCP_200um_G1200um.hdf5
MasterLattice/Data_Files/DCP_200um_G1200um.sdds
MasterLattice/Data_Files/DCP_200um_G1200um.txt
MasterLattice/Data_Files/DCP_200um_G1200um_new.hdf5
MasterLattice/Data_Files/HRRG_1D_RF.dat
MasterLattice/Data_Files/HRRG_1D_RF.gdf
MasterLattice/Data_Files/HRRG_1D_RF.hdf5
MasterLattice/Data_Files/HRRG_1D_RF.opal
MasterLattice/Data_Files/HRRG_1D_RF.test.hdf5
MasterLattice/Data_Files/HRRG_Simulated_Bucking_Solenoid_2024.gdf
MasterLattice/Data_Files/HRRG_Simulated_Bucking_Solenoid_2024.hdf5
MasterLattice/Data_Files/HRRG_Simulated_Bucking_Solenoid_2024.test.hdf5
MasterLattice/Data_Files/HRRG_Simulated_Bucking_Solenoid_2024.txt
MasterLattice/Data_Files/HRRG_Simulated_Combined_Solenoid_2024.gdf
MasterLattice/Data_Files/HRRG_Simulated_Combined_Solenoid_2024.hdf5
MasterLattice/Data_Files/HRRG_Simulated_Combined_Solenoid_2024.txt
MasterLattice/Data_Files/HRRG_Simulated_Main_Solenoid_2024.gdf
MasterLattice/Data_Files/HRRG_Simulated_Main_Solenoid_2024.hdf5
MasterLattice/Data_Files/HRRG_Simulated_Main_Solenoid_2024.txt
MasterLattice/Data_Files/HRRG_combined_sols_100mm_onaxis.dat
MasterLattice/Data_Files/HRRG_combined_sols_100mm_onaxis.gdf
MasterLattice/Data_Files/HRRG_combined_sols_100mm_onaxis.hdf5
MasterLattice/Data_Files/HRRG_combined_sols_100mm_onaxis.txt
MasterLattice/Data_Files/L1entrancecell.dat
MasterLattice/Data_Files/L1exitcell.dat
MasterLattice/Data_Files/L1singlecell.dat
MasterLattice/Data_Files/LRRG_Measured_Bucking_Solenoid_2019.gdf
MasterLattice/Data_Files/LRRG_Measured_Bucking_Solenoid_2019.txt
MasterLattice/Data_Files/LRRG_Measured_Combined_Solenoid_2019.txt
MasterLattice/Data_Files/LRRG_Measured_Main_Solenoid_2019.gdf
MasterLattice/Data_Files/LRRG_Measured_Main_Solenoid_2019.txt
MasterLattice/Data_Files/Sol_focusing_1D.T7
MasterLattice/Data_Files/SwissFEL_linac_sols.dat
masterlattice-1.0.0.dist-info/METADATA
masterlattice-1.0.0.dist-info/WHEEL
masterlattice-1.0.0.dist-info/top_level.txt
masterlattice-1.0.0.dist-info/RECORD
