Metadata-Version: 2.4
Name: MasterLattice
Version: 1.0.0
Summary: Files defining the CLARA lattice
Home-page: https://github.com/astec-stfc/masterlattice
Author: James Jones
Author-email: james.jones@stfc.ac.uk
Classifier: License :: OSI Approved :: GNU General Public License v3 (GPLv3)
Dynamic: author
Dynamic: author-email
Dynamic: classifier
Dynamic: description
Dynamic: description-content-type
Dynamic: home-page
Dynamic: summary
